{
  "report_name": "kilroy_realty_sustainability_report_2017",
  "report_title": "Kilroy Realty 2017 Sustainability Report",
  "emissions": {
    "scope_1": {
      "2016": [
        {
          "value": 4059,
          "unit": "Tonnes",
          "label": "Absolute Consumption"
        },
        {
          "value": 3110,
          "unit": "Tonnes",
          "label": "Like-for-Like Consumption"
        }
      ],
      "2017": [
        {
          "value": 4641,
          "unit": "Tonnes",
          "label": "Absolute Consumption"
        },
        {
          "value": 3296,
          "unit": "Tonnes",
          "label": "Like-for-Like Consumption"
        }
      ]
    },
    "scope_2_location_based": {
      "2016": [
        {
          "value": 44145,
          "unit": "Tonnes",
          "label": "Absolute Consumption"
        },
        {
          "value": 39484,
          "unit": "Tonnes",
          "label": "Like-for-Like Consumption"
        }
      ],
      "2017": [
        {
          "value": 42947,
          "unit": "Tonnes",
          "label": "Absolute Consumption"
        },
        {
          "value": 35490,
          "unit": "Tonnes",
          "label": "Like-for-Like Consumption"
        }
      ]
    },
    "scope_2_market_based": {},
    "scope_3": {}
  }
}