{
  "report": "lundin gold inc_2022_report",
  "query": "What are the total CO2 emissions in different years? Include Scope 1, Scope 2, and Scope 3 emissions if available.",
  "timestamp": "2026-06-12 09:54:29",
  "run_ts": "0612_0953",
  "top_10_pages": [
    12,
    11,
    6,
    10,
    13,
    27,
    30,
    23,
    40,
    24
  ],
  "top_10_scores": [
    25.269203186035156,
    24.6927547454834,
    24.36893653869629,
    24.103713989257812,
    23.85266876220703,
    23.850406646728516,
    23.668468475341797,
    23.63773536682129,
    23.63266944885254,
    23.62763214111328
  ],
  "top_10_data": [
    {
      "page": 12,
      "score": 25.269203186035156
    },
    {
      "page": 11,
      "score": 24.6927547454834
    },
    {
      "page": 6,
      "score": 24.36893653869629
    },
    {
      "page": 10,
      "score": 24.103713989257812
    },
    {
      "page": 13,
      "score": 23.85266876220703
    },
    {
      "page": 27,
      "score": 23.850406646728516
    },
    {
      "page": 30,
      "score": 23.668468475341797
    },
    {
      "page": 23,
      "score": 23.63773536682129
    },
    {
      "page": 40,
      "score": 23.63266944885254
    },
    {
      "page": 24,
      "score": 23.62763214111328
    }
  ]
}