{
  "report": "varta ag_2021_report",
  "query": "What are the total CO2 emissions in different years? Include Scope 1, Scope 2, and Scope 3 emissions if available.",
  "timestamp": "2026-06-12 09:54:37",
  "run_ts": "0612_0953",
  "top_10_pages": [
    38,
    26,
    39,
    41,
    23,
    34,
    28,
    27,
    0,
    25
  ],
  "top_10_scores": [
    25.279462814331055,
    24.795825958251953,
    24.517391204833984,
    24.329145431518555,
    23.99073028564453,
    23.73946762084961,
    23.685155868530273,
    23.684356689453125,
    23.592605590820312,
    23.5386962890625
  ],
  "top_10_data": [
    {
      "page": 38,
      "score": 25.279462814331055
    },
    {
      "page": 26,
      "score": 24.795825958251953
    },
    {
      "page": 39,
      "score": 24.517391204833984
    },
    {
      "page": 41,
      "score": 24.329145431518555
    },
    {
      "page": 23,
      "score": 23.99073028564453
    },
    {
      "page": 34,
      "score": 23.73946762084961
    },
    {
      "page": 28,
      "score": 23.685155868530273
    },
    {
      "page": 27,
      "score": 23.684356689453125
    },
    {
      "page": 0,
      "score": 23.592605590820312
    },
    {
      "page": 25,
      "score": 23.5386962890625
    }
  ]
}